{"name":"Bigender","id":"bigender_2014","year":"2014","svg":"<svg xmlns=\"http://www.w3.org/2000/svg\" viewBox=\"0 0 512 308\"><path d=\"M0 0h512v44H0z\" fill=\"#c479a2\"></path><path d=\"M0 44h512v44H0z\" fill=\"#eda5cd\"></path><path d=\"M0 88h512v132H0z\" fill=\"#d5c7e8\"></path><path d=\"M0 132h512v44H0z\" fill=\"#fff\"></path><path d=\"M0 220h512v44H0z\" fill=\"#9ac7e8\"></path><path d=\"M0 264h512v44H0z\" fill=\"#6d82d1\"></path></svg>","colors":[{"name":"deep pink","hexCode":"#C479A0","r":196,"g":121,"b":160},{"name":"pink","hexCode":"#ECA6CB","r":236,"g":166,"b":203},{"name":"lilac","hexCode":"#D6C7E7","r":214,"g":199,"b":231},{"name":"white","hexCode":"#FFFFFF","r":255,"g":255,"b":255},{"name":"baby blue","hexCode":"#9BC7E8","r":155,"g":199,"b":232},{"name":"deep blue","hexCode":"#6B83CF","r":107,"g":131,"b":207}]}